{"statistics":{"identical":10,"minorChanges":31,"relatedMeaning":0},"text":{"comparison":{"identical":{"source":{"chars":{"starts":[206145],"lengths":[79]},"words":{"starts":[33721],"lengths":[9]}},"suspected":{"chars":{"starts":[1571],"lengths":[77]},"words":{"starts":[217],"lengths":[9]}}},"minorChanges":{"source":{"chars":{"starts":[783157],"lengths":[202]},"words":{"starts":[118003],"lengths":[30]}},"suspected":{"chars":{"starts":[2433],"lengths":[187]},"words":{"starts":[338],"lengths":[27]}}},"relatedMeaning":{"source":{"chars":{"starts":[],"lengths":[]},"words":{"starts":[],"lengths":[]}},"suspected":{"chars":{"starts":[],"lengths":[]},"words":{"starts":[],"lengths":[]}}}},"value":"\nM. Beran, Statistical Continuum Theories, 1968.\n\n\nN. Bilger, F. Auslender, M. Bornert, J. Michel, H. Moulinec et al., Effect of a non uniform distribution of voids on the plastic response of voided materials: a computational and statistical analysis, Int. J. Solids Struct, vol.42, pp.517-538, 2005.\n\n\nM. Bornert, Homogénéisation en mécanique des matériaux 1: Matériaux aléatoires élastiques et milieux périodiques, pp.133-221, 2001.\n\n\nM. Bornert, C. Stolz, and A. Zaoui, Morphologically representative pattern-based bounding in elasticity, J. Mech. Phys. Solids, vol.44, pp.307-331, 1996.\n\n\nG. Casella and R. Berger, Statistical Inference. Duxbury, United States. CEA, 2001.\n\n\nR. M. Christensen and K. H. Lo, Solution for effective shear properties in three phase sphere and cylinder models, J. Mech. Phys. Solids, vol.27, pp.315-330, 1979.\n\n\nM. Danielsson, D. Parks, and M. Boyce, Micromechanics, macromechanics and constitutive modeling of the elasto-viscoplastic deformation of rubbertoughened glassy polymers, J. Mech. Phys. Solids, vol.55, pp.533-561, 2007.\n\n\nI. Doghri, L. Adam, and N. Bilger, Mean-field homogenization of elastoviscoplastic composites based on a general incrementally affine linearization method, Int. J. Plast, vol.26, pp.219-238, 2010.\n\n\nJ. D. Eshelby, The determination of the elastic field of an ellipsoidal inclusion, and related problems, Proc. R. Soc. Lond. A A421, pp.376-396, 1957.\n\n\nI. Gitman, H. Askes, and L. Sluys, Representative volume: existence and size determination, Eng. Fracture Mech, vol.74, pp.2518-2534, 2007.\n\n\nA. Gusev, Representative volume element size for elastic composites: a numerical study, J. Mech. Phys. Solids, vol.45, issue.9, pp.1449-1459, 1997.\n\n\nZ. Hashin, The elastic moduli of heterogeneous materials, J. Appl. Mech, vol.29, pp.143-150, 1962.\n\n\nZ. Hashin and B. W. Rosen, The elastic moduli of fiber-reinforced materials, J. Appl. Mech, vol.31, pp.223-232, 1964.\n\n\nZ. Hashin and S. Shtrikman, A variational approach to the theorie of the elastic behavior of multiphase material, J. Mech. Phys. Solids, vol.11, pp.127-140, 1963.\n\n\nC. Huet, Application of variational concepts to size effects in elastic heterogeneous bodies, J. Mech. Phys. Solids, vol.38, pp.813-841, 1990.\n\n\nM. Jiang, K. Alzebdeh, I. Jasiuk, and M. Ostoja-starzewski, Scale and boundary conditions effects in elastic properties of random composites, Acta Mech, vol.148, issue.1-4, pp.63-78, 2001.\n\n\nT. Kanit, S. Forest, I. Galliet, V. Mounoury, and D. Jeulin, Determination of the size of the representative volume element for random composites: statistical and numerical approach, Int. J. Solids Struct, vol.40, pp.3647-3679, 2003.\n\n\nE. Kroner, Berechnung der elastischen konstanten des vielkrilstalls aus den konstanten des einkristalls, Z. Phys, vol.151, pp.504-518, 1958.\n\n\nN. Lahellec and P. Suquet, Nonlinear composites: a linearization procedure, exact to second-order in contrast and for which the strain-energy and affine formulations coincide, C.R. Mec, vol.332, pp.693-700, 2004.\nURL : https://hal.archives-ouvertes.fr/hal-00088254\n\n\nN. Lahellec and P. Suquet, On the effective behavior of nonlinear inelastic composites: I Incremental variational principles, J. Mech. Phys. Solids, vol.55, pp.1932-1963, 2007.\nURL : https://hal.archives-ouvertes.fr/hal-00214209\n\n\nR. Masson and A. Zaoui, Self-consistent estimates for the rate-dependent elastoplastic behaviour of polycrystalline materials, J. Mech. Phys. Solids, vol.47, pp.1543-1568, 1999.\nURL : https://hal.archives-ouvertes.fr/hal-00111618\n\n\nT. Mori and K. Tanaka, Average stress in matrix and average elastic energy of materials with misfitting inclusions, Acta Metall, vol.21, pp.597-629, 1973.\n\n\nS. Nemat-nasser and M. Hori, Micromechanics: overall Properties of Heterogenous Materials, 1993.\n\n\nM. Ostoja-starzewski, Random field models of heterogeneous materials, Int. J. Solids Struct, vol.35, pp.2429-2455, 1998.\n\n\nM. Ostoja-starzewski, Material spatial randomness: from statistical to representative volume element, Prob. Eng. Mech, vol.21, pp.112-132, 2006.\n\n\nG. Papanicolaou and S. Varadhan, Boundary Value Problems with Rapidly Oscillating Random Coefficients, pp.835-873, 1978.\n\n\nC. Pelissou, J. Baccou, Y. Monerie, and F. Perales, Determination of the size of the representative volume element for random quasi-brittle composites, Int. J. Sol. Struct, vol.46, pp.2842-2855, 2009.\nURL : https://hal.archives-ouvertes.fr/hal-02095427\n\n\nP. Castañeda and P. , Second-order homogeneisation estimates for nonlinear composites incorporating field fluctuations: I-theory, J. Mech. Phys. Solids, vol.50, pp.737-757, 2002.\n\n\nP. Castañeda, P. Suquet, and P. , Nonlinear composites, Advances in Applied Mechanics, vol.34, pp.213-302, 1997.\n\n\nP. Castañeda, P. Willis, and J. , The effect of spatial distribution on the effective behavior of composite materials and cracked media, J. Mech. Phys. Solids, vol.43, issue.12, pp.1919-1951, 1995.\n\n\nS. Ranganathan and M. Ostoja-starzewski, Scaling function, anisotropy and the size of RVE in elastic random polycrystals, J. Mech. Phys. Solids, vol.56, pp.2773-2791, 2008.\n\n\nA. Reuss, Calculation of the flow limits of mixed crystals on the basis of the plasticity of mono-crystals, Z. Angew. Math. Mech, vol.9, pp.49-58, 1929.\n\n\nM. Rintoul and S. Torquato, Reconstruction of the structure of dispersions, J. Colloid Interface Sci, vol.186, issue.2, pp.467-476, 1997.\n\n\nK. Sab, On the homogenization and the simulation of random materials, Eur. J. Mech. A/Solids, vol.11, pp.585-607, 1992.\n\n\nM. Salmi, Homogénéisation des composites linéaires: étude de la variabilité des comportements, 2011.\n\n\nM. Salmi, F. Auslender, M. Bornert, and M. Fogli, Various estimates of representative volume element sizes based on a statistical analysis of the apparent behavior of random linear composites, Comptes Rendus Mécanique, 2012.\nURL : https://hal.archives-ouvertes.fr/hal-01157361\n\n\nE. Sanchez-palencia, , vol.272, 1987.\n\n\nJ. Schoberl, H. Gerstmayr, and R. Gaisbauer, Netgen -Automatic mesh generator, 2003.\n\n\nC. Stolz and A. Zaoui, Analyse morphologique et approches variationnelles du comportement d'un milieu élastique hétérogène, C.R. Acad. Sci, vol.312, pp.143-150, 1991.\n\n\nW. Voigt, 1889. über die beziehung zwischen den beiden elasticitätsconstanten isotroper körper, Ann. Phys. (Leipzig), vol.38, pp.573-587\n\n\nL. Walpole, Elastic Behavior of Composite Materials: Theoretical Foundations, vol.21, pp.160-242, 1981.\n\n\nJ. Willis, Bounds and self-consistent estimates for the overall properties of anisotropic composites, J. Mech. Phys. Solids, vol.25, pp.185-202, 1977.\n\n\nJ. Willis, Variational and related methods for the overall properties of composites, Adv. Appl. Mech, vol.21, pp.1-78, 1981.\n\n\nF. Willot and . Jeulin, Elastic behavior of composites containing boolean random sets of inhomogeneities, Int. J. Eng. Sci, vol.47, pp.313-324, 2009.\nURL : https://hal.archives-ouvertes.fr/hal-00426398\n\n\nF. Willot, Y. Pellegrini, and P. Ponte-castañeda, Localization of elastic deformation in strongly anisotropic, porous, linear materials with periodic microstructures: exact solutions and dilute expansions, J. Mech. Phys. Solids, vol.56, issue.4, pp.1245-1268, 2008.\nURL : https://hal.archives-ouvertes.fr/cea-00412543\n\n\n","pages":{"startPosition":[0,5001]}},"html":{"comparison":{"identical":{"groupId":[0,0,0,0,0,0,0,0,0,0,0,0,0,0,0,0,0,0,0],"source":{"chars":{"starts":[4731861,4731861,4731892,4731900,4731922,4731930,4731953,4731961,4731981,4731989,4732008,4732016,4732039,4732047,4732119,4732136,4732144,4732169,4732177],"lengths":[15,15,1,6,1,7,1,4,1,3,1,7,1,11,1,1,9,1,7]},"words":{"starts":[33721,33721,33721,33721,33721,33721,33721,33721,33721,33721,33721,33721,33721,33721,33721,33721,33721,33721,33721],"lengths":[9,9,9,9,9,9,9,9,9,9,9,9,9,9,9,9,9,9,9]}},"suspected":{"chars":{"starts":[6238,6356,6238,6238,6238,6238,6238,6238,6238,6238,6238,6238,6238,6238,6238,6238,6238,6238,6238],"lengths":[76,1,76,76,76,76,76,76,76,76,76,76,76,76,76,76,76,76,76]},"words":{"starts":[217,217,217,217,217,217,217,217,217,217,217,217,217,217,217,217,217,217,217],"lengths":[9,9,9,9,9,9,9,9,9,9,9,9,9,9,9,9,9,9,9]}}},"minorChanges":{"groupId":[1,1,1,1,1,1,1,1,1,1,1,1,1,1,1,1,1,1,1,1,1,1,1,1,1,1,1,1,1,1,1,1,1,1,1,1,1,1,1,1,1,1,1,1,1,1,1,1,1,1,1,1,1,1,1,1,1,1,1,1,1,1,1,1,1,1],"source":{"chars":{"starts":[7657569,7657569,7657569,7657569,7657569,7657594,7657602,7657620,7657628,7657654,7657662,7657680,7657688,7657711,7657719,7657737,7657745,7657763,7657771,7657789,7657797,7657815,7657823,7657841,7657849,7657868,7657876,7657894,7657902,7657926,7657934,7657953,7657961,7657991,7657999,7658017,7658025,7658044,7658052,7658072,7658080,7658098,7658106,7658125,7658133,7658205,7658227,7658235,7658257,7658265,7658288,7658296,7658315,7658323,7658345,7658353,7658383,7658391,7658418,7658426,7658445,7658453,7658478,7658486,7658512,7658538],"lengths":[5,5,5,5,5,1,2,1,7,1,2,1,7,1,2,1,2,1,2,1,2,1,2,1,3,1,2,1,8,1,3,1,14,1,2,1,3,1,4,1,2,1,3,1,9,6,1,6,1,7,1,3,1,6,1,11,1,11,1,3,1,9,1,10,1,13]},"words":{"starts":[118003,118003,118003,118003,118003,118003,118003,118003,118003,118003,118003,118003,118003,118003,118003,118003,118003,118003,118003,118003,118003,118003,118003,118003,118003,118003,118003,118003,118003,118003,118003,118003,118003,118003,118003,118003,118003,118003,118003,118003,118003,118003,118003,118003,118003,118003,118003,118003,118003,118003,118003,118003,118003,118003,118003,118003,118003,118003,118003,118003,118003,118003,118003,118003,118003,118003],"lengths":[30,30,30,30,30,30,30,30,30,30,30,30,30,30,30,30,30,30,30,30,30,30,30,30,30,30,30,30,30,30,30,30,30,30,30,30,30,30,30,30,30,30,30,30,30,30,30,30,30,30,30,30,30,30,30,30,30,30,30,30,30,30,30,30,30,30]}},"suspected":{"chars":{"starts":[10319,10385,10417,10579,10622,10319,10319,10319,10319,10319,10319,10319,10319,10319,10319,10319,10319,10319,10319,10319,10319,10319,10319,10319,10319,10319,10319,10319,10319,10319,10319,10319,10319,10319,10319,10319,10319,10319,10319,10319,10319,10319,10319,10319,10319,10319,10319,10319,10319,10319,10319,10319,10319,10319,10319,10319,10319,10319,10319,10319,10319,10319,10319,10319,10319,10319],"lengths":[59,2,120,2,4,59,59,59,59,59,59,59,59,59,59,59,59,59,59,59,59,59,59,59,59,59,59,59,59,59,59,59,59,59,59,59,59,59,59,59,59,59,59,59,59,59,59,59,59,59,59,59,59,59,59,59,59,59,59,59,59,59,59,59,59,59]},"words":{"starts":[338,338,338,338,338,338,338,338,338,338,338,338,338,338,338,338,338,338,338,338,338,338,338,338,338,338,338,338,338,338,338,338,338,338,338,338,338,338,338,338,338,338,338,338,338,338,338,338,338,338,338,338,338,338,338,338,338,338,338,338,338,338,338,338,338,338],"lengths":[27,27,27,27,27,27,27,27,27,27,27,27,27,27,27,27,27,27,27,27,27,27,27,27,27,27,27,27,27,27,27,27,27,27,27,27,27,27,27,27,27,27,27,27,27,27,27,27,27,27,27,27,27,27,27,27,27,27,27,27,27,27,27,27,27,27]}}},"relatedMeaning":{"groupId":[],"source":{"chars":{"starts":[],"lengths":[]},"words":{"starts":[],"lengths":[]}},"suspected":{"chars":{"starts":[],"lengths":[]},"words":{"starts":[],"lengths":[]}}}},"value":"<html><head><base href=\"https://enpc.hal.science/hal-01157362v1/html_references\" target=\"_blank\"></head><body>\n<p class=\"ref\" id=\"24642210\"><span class=\"citation-reference\"><span class=\"authors-reference\">M. Beran</span>, <span class=\"title-reference\">Statistical Continuum Theories</span><span class=\"date-reference\">, <span class=\"date-reference-value\">1968</span>.</span></span><span class=\"identifiers-reference\"></span>\n</p>\n\n<p class=\"ref\" id=\"24642211\"><span class=\"citation-reference\"><span class=\"authors-reference\">N. Bilger, F. Auslender, M. Bornert, J. Michel, H. Moulinec et al.</span>, <span class=\"title-reference\">Effect of a non uniform distribution of voids on the plastic response of voided materials: a computational and statistical analysis</span><span class=\"titleEvent-reference\">, <span class=\"titleEvent-reference-value\">Int. J. Solids Struct</span></span><span class=\"vol-reference\">, vol.<span class=\"vol-reference-value\">42</span></span><span class=\"pages-reference\">, pp.<span class=\"pages-reference-value\">517-538</span></span><span class=\"date-reference\">, <span class=\"date-reference-value\">2005</span>.</span></span><span class=\"identifiers-reference\"></span>\n</p>\n\n<p class=\"ref\" id=\"24642212\"><span class=\"citation-reference\"><span class=\"authors-reference\">M. Bornert</span>, <span class=\"title-reference\">Homogénéisation en mécanique des matériaux 1: Matériaux aléatoires élastiques et milieux périodiques</span><span class=\"pages-reference\">, pp.<span class=\"pages-reference-value\">133-221</span></span><span class=\"date-reference\">, <span class=\"date-reference-value\">2001</span>.</span></span><span class=\"identifiers-reference\"></span>\n</p>\n\n<p class=\"ref\" id=\"24642213\"><span class=\"citation-reference\"><span class=\"authors-reference\">M. Bornert, C. Stolz, and A. Zaoui</span>, <span class=\"title-reference\">Morphologically representative pattern-based bounding in elasticity</span><span class=\"titleEvent-reference\">, <span class=\"titleEvent-reference-value\">J. Mech. Phys. Solids</span></span><span class=\"vol-reference\">, vol.<span class=\"vol-reference-value\">44</span></span><span class=\"pages-reference\">, pp.<span class=\"pages-reference-value\">307-331</span></span><span class=\"date-reference\">, <span class=\"date-reference-value\">1996</span>.</span></span><span class=\"identifiers-reference\"></span>\n</p>\n\n<p class=\"ref\" id=\"24642214\"><span class=\"citation-reference\"><span class=\"authors-reference\">G. Casella and R. Berger</span>, <span class=\"title-reference\">Statistical Inference. Duxbury, United States. CEA</span><span class=\"date-reference\">, <span class=\"date-reference-value\">2001</span>.</span></span><span class=\"identifiers-reference\"></span>\n</p>\n\n<p class=\"ref\" id=\"24642215\"><span class=\"citation-reference\"><span class=\"authors-reference\">R. M. Christensen and K. H. Lo</span>, <span class=\"title-reference\">Solution for effective shear properties in three phase sphere and cylinder models</span><span class=\"titleEvent-reference\">, <span class=\"titleEvent-reference-value\">J. Mech. Phys. Solids</span></span><span class=\"vol-reference\">, vol.<span class=\"vol-reference-value\">27</span></span><span class=\"pages-reference\">, pp.<span class=\"pages-reference-value\">315-330</span></span><span class=\"date-reference\">, <span class=\"date-reference-value\">1979</span>.</span></span><span class=\"identifiers-reference\"></span>\n</p>\n\n<p class=\"ref\" id=\"24642216\"><span class=\"citation-reference\"><span class=\"authors-reference\">M. Danielsson, D. Parks, and M. Boyce</span>, <span class=\"title-reference\">Micromechanics, macromechanics and constitutive modeling of the elasto-viscoplastic deformation of rubbertoughened glassy polymers</span><span class=\"titleEvent-reference\">, <span class=\"titleEvent-reference-value\">J. Mech. Phys. Solids</span></span><span class=\"vol-reference\">, vol.<span class=\"vol-reference-value\">55</span></span><span class=\"pages-reference\">, pp.<span class=\"pages-reference-value\">533-561</span></span><span class=\"date-reference\">, <span class=\"date-reference-value\">2007</span>.</span></span><span class=\"identifiers-reference\"></span>\n</p>\n\n<p class=\"ref\" id=\"24642217\"><span class=\"citation-reference\"><span class=\"authors-reference\">I. Doghri, L. Adam, and N. Bilger</span>, <span class=\"title-reference\">Mean-field homogenization of elastoviscoplastic composites based on a general incrementally affine linearization method</span><span class=\"titleEvent-reference\">, <span class=\"titleEvent-reference-value\">Int. J. Plast</span></span><span class=\"vol-reference\">, vol.<span class=\"vol-reference-value\">26</span></span><span class=\"pages-reference\">, pp.<span class=\"pages-reference-value\">219-238</span></span><span class=\"date-reference\">, <span class=\"date-reference-value\">2010</span>.</span></span><span class=\"identifiers-reference\"></span>\n</p>\n\n<p class=\"ref\" id=\"24642218\"><span class=\"citation-reference\"><span class=\"authors-reference\">J. D. Eshelby</span>, <span class=\"title-reference\">The determination of the elastic field of an ellipsoidal inclusion, and related problems</span><span class=\"titleEvent-reference\">, <span class=\"titleEvent-reference-value\">Proc. R. Soc. Lond. A A421</span></span><span class=\"pages-reference\">, pp.<span class=\"pages-reference-value\">376-396</span></span><span class=\"date-reference\">, <span class=\"date-reference-value\">1957</span>.</span></span><span class=\"identifiers-reference\"></span>\n</p>\n\n<p class=\"ref\" id=\"24642219\"><span class=\"citation-reference\"><span class=\"authors-reference\">I. Gitman, H. Askes, and L. Sluys</span>, <span class=\"title-reference\">Representative volume: existence and size determination</span><span class=\"titleEvent-reference\">, <span class=\"titleEvent-reference-value\">Eng. Fracture Mech</span></span><span class=\"vol-reference\">, vol.<span class=\"vol-reference-value\">74</span></span><span class=\"pages-reference\">, pp.<span class=\"pages-reference-value\">2518-2534</span></span><span class=\"date-reference\">, <span class=\"date-reference-value\">2007</span>.</span></span><span class=\"identifiers-reference\"></span>\n</p>\n\n<p class=\"ref\" id=\"24642220\"><span class=\"citation-reference\"><span class=\"authors-reference\">A. Gusev</span>, <span class=\"title-reference\">Representative volume element size for elastic composites: a numerical study</span><span class=\"titleEvent-reference\">, <span class=\"titleEvent-reference-value\">J. Mech. Phys. Solids</span></span><span class=\"vol-reference\">, vol.<span class=\"vol-reference-value\">45</span></span><span class=\"issue-reference\">, issue.<span class=\"issue-reference-value\">9</span></span><span class=\"pages-reference\">, pp.<span class=\"pages-reference-value\">1449-1459</span></span><span class=\"date-reference\">, <span class=\"date-reference-value\">1997</span>.</span></span><span class=\"identifiers-reference\"></span>\n</p>\n\n<p class=\"ref\" id=\"24642221\"><span class=\"citation-reference\"><span class=\"authors-reference\">Z. Hashin</span>, <span class=\"title-reference\">The elastic moduli of heterogeneous materials</span><span class=\"titleEvent-reference\">, <span class=\"titleEvent-reference-value\">J. Appl. Mech</span></span><span class=\"vol-reference\">, vol.<span class=\"vol-reference-value\">29</span></span><span class=\"pages-reference\">, pp.<span class=\"pages-reference-value\">143-150</span></span><span class=\"date-reference\">, <span class=\"date-reference-value\">1962</span>.</span></span><span class=\"identifiers-reference\"></span>\n</p>\n\n<p class=\"ref\" id=\"24642222\"><span class=\"citation-reference\"><span class=\"authors-reference\">Z. Hashin and B. W. Rosen</span>, <span class=\"title-reference\">The elastic moduli of fiber-reinforced materials</span><span class=\"titleEvent-reference\">, <span class=\"titleEvent-reference-value\">J. Appl. Mech</span></span><span class=\"vol-reference\">, vol.<span class=\"vol-reference-value\">31</span></span><span class=\"pages-reference\">, pp.<span class=\"pages-reference-value\">223-232</span></span><span class=\"date-reference\">, <span class=\"date-reference-value\">1964</span>.</span></span><span class=\"identifiers-reference\"></span>\n</p>\n\n<p class=\"ref\" id=\"24642223\"><span class=\"citation-reference\"><span class=\"authors-reference\">Z. Hashin and S. Shtrikman</span>, <span class=\"title-reference\">A variational approach to the theorie of the elastic behavior of multiphase material</span><span class=\"titleEvent-reference\">, <span class=\"titleEvent-reference-value\">J. Mech. Phys. Solids</span></span><span class=\"vol-reference\">, vol.<span class=\"vol-reference-value\">11</span></span><span class=\"pages-reference\">, pp.<span class=\"pages-reference-value\">127-140</span></span><span class=\"date-reference\">, <span class=\"date-reference-value\">1963</span>.</span></span><span class=\"identifiers-reference\"></span>\n</p>\n\n<p class=\"ref\" id=\"24642224\"><span class=\"citation-reference\"><span class=\"authors-reference\">C. Huet</span>, <span class=\"title-reference\">Application of variational concepts to size effects in elastic heterogeneous bodies</span><span class=\"titleEvent-reference\">, <span class=\"titleEvent-reference-value\">J. Mech. Phys. Solids</span></span><span class=\"vol-reference\">, vol.<span class=\"vol-reference-value\">38</span></span><span class=\"pages-reference\">, pp.<span class=\"pages-reference-value\">813-841</span></span><span class=\"date-reference\">, <span class=\"date-reference-value\">1990</span>.</span></span><span class=\"identifiers-reference\"></span>\n</p>\n\n<p class=\"ref\" id=\"24642225\"><span class=\"citation-reference\"><span class=\"authors-reference\">M. Jiang, K. Alzebdeh, I. Jasiuk, and M. Ostoja-starzewski</span>, <span class=\"title-reference\">Scale and boundary conditions effects in elastic properties of random composites</span><span class=\"titleEvent-reference\">, <span class=\"titleEvent-reference-value\">Acta Mech</span></span><span class=\"vol-reference\">, vol.<span class=\"vol-reference-value\">148</span></span><span class=\"issue-reference\">, issue.<span class=\"issue-reference-value\">1-4</span></span><span class=\"pages-reference\">, pp.<span class=\"pages-reference-value\">63-78</span></span><span class=\"date-reference\">, <span class=\"date-reference-value\">2001</span>.</span></span><span class=\"identifiers-reference\"></span>\n</p>\n\n<p class=\"ref\" id=\"24642226\"><span class=\"citation-reference\"><span class=\"authors-reference\">T. Kanit, S. Forest, I. Galliet, V. Mounoury, and D. Jeulin</span>, <span class=\"title-reference\">Determination of the size of the representative volume element for random composites: statistical and numerical approach</span><span class=\"titleEvent-reference\">, <span class=\"titleEvent-reference-value\">Int. J. Solids Struct</span></span><span class=\"vol-reference\">, vol.<span class=\"vol-reference-value\">40</span></span><span class=\"pages-reference\">, pp.<span class=\"pages-reference-value\">3647-3679</span></span><span class=\"date-reference\">, <span class=\"date-reference-value\">2003</span>.</span></span><span class=\"identifiers-reference\"></span>\n</p>\n\n<p class=\"ref\" id=\"24642227\"><span class=\"citation-reference\"><span class=\"authors-reference\">E. Kroner</span>, <span class=\"title-reference\">Berechnung der elastischen konstanten des vielkrilstalls aus den konstanten des einkristalls</span><span class=\"titleEvent-reference\">, <span class=\"titleEvent-reference-value\">Z. Phys</span></span><span class=\"vol-reference\">, vol.<span class=\"vol-reference-value\">151</span></span><span class=\"pages-reference\">, pp.<span class=\"pages-reference-value\">504-518</span></span><span class=\"date-reference\">, <span class=\"date-reference-value\">1958</span>.</span></span><span class=\"identifiers-reference\"></span>\n</p>\n\n<p class=\"ref\" id=\"24642228\"><span class=\"citation-reference\"><span class=\"authors-reference\">N. Lahellec and P. Suquet</span>, <span class=\"title-reference\">Nonlinear composites: a linearization procedure, exact to second-order in contrast and for which the strain-energy and affine formulations coincide</span><span class=\"titleEvent-reference\">, <span class=\"titleEvent-reference-value\">C.R. Mec</span></span><span class=\"vol-reference\">, vol.<span class=\"vol-reference-value\">332</span></span><span class=\"pages-reference\">, pp.<span class=\"pages-reference-value\">693-700</span></span><span class=\"date-reference\">, <span class=\"date-reference-value\">2004</span>.</span></span><span class=\"identifiers-reference\"><span class=\"url-reference\"><br>\nURL : <a class=\"url-reference-value\" target=\"_blank\" href=\"https://hal.archives-ouvertes.fr/hal-00088254\">https://hal.archives-ouvertes.fr/hal-00088254</a></span></span>\n</p>\n\n<p class=\"ref\" id=\"24642229\"><span class=\"citation-reference\"><span class=\"authors-reference\">N. Lahellec and P. Suquet</span>, <span class=\"title-reference\">On the effective behavior of nonlinear inelastic composites: I Incremental variational principles</span><span class=\"titleEvent-reference\">, <span class=\"titleEvent-reference-value\">J. Mech. Phys. Solids</span></span><span class=\"vol-reference\">, vol.<span class=\"vol-reference-value\">55</span></span><span class=\"pages-reference\">, pp.<span class=\"pages-reference-value\">1932-1963</span></span><span class=\"date-reference\">, <span class=\"date-reference-value\">2007</span>.</span></span><span class=\"identifiers-reference\"><span class=\"url-reference\"><br>\nURL : <a class=\"url-reference-value\" target=\"_blank\" href=\"https://hal.archives-ouvertes.fr/hal-00214209\">https://hal.archives-ouvertes.fr/hal-00214209</a></span></span>\n</p>\n\n<p class=\"ref\" id=\"24642230\"><span class=\"citation-reference\"><span class=\"authors-reference\">R. Masson and A. Zaoui</span>, <span class=\"title-reference\">Self-consistent estimates for the rate-dependent elastoplastic behaviour of polycrystalline materials</span><span class=\"titleEvent-reference\">, <span class=\"titleEvent-reference-value\">J. Mech. Phys. Solids</span></span><span class=\"vol-reference\">, vol.<span class=\"vol-reference-value\">47</span></span><span class=\"pages-reference\">, pp.<span class=\"pages-reference-value\">1543-1568</span></span><span class=\"date-reference\">, <span class=\"date-reference-value\">1999</span>.</span></span><span class=\"identifiers-reference\"><span class=\"url-reference\"><br>\nURL : <a class=\"url-reference-value\" target=\"_blank\" href=\"https://hal.archives-ouvertes.fr/hal-00111618\">https://hal.archives-ouvertes.fr/hal-00111618</a></span></span>\n</p>\n\n<p class=\"ref\" id=\"24642231\"><span class=\"citation-reference\"><span class=\"authors-reference\">T. Mori and K. Tanaka</span>, <span class=\"title-reference\">Average stress in matrix and average elastic energy of materials with misfitting inclusions</span><span class=\"titleEvent-reference\">, <span class=\"titleEvent-reference-value\">Acta Metall</span></span><span class=\"vol-reference\">, vol.<span class=\"vol-reference-value\">21</span></span><span class=\"pages-reference\">, pp.<span class=\"pages-reference-value\">597-629</span></span><span class=\"date-reference\">, <span class=\"date-reference-value\">1973</span>.</span></span><span class=\"identifiers-reference\"></span>\n</p>\n\n<p class=\"ref\" id=\"24642232\"><span class=\"citation-reference\"><span class=\"authors-reference\">S. Nemat-nasser and M. Hori</span>, <span class=\"title-reference\">Micromechanics: overall Properties of Heterogenous Materials</span><span class=\"date-reference\">, <span class=\"date-reference-value\">1993</span>.</span></span><span class=\"identifiers-reference\"></span>\n</p>\n\n<p class=\"ref\" id=\"24642233\"><span class=\"citation-reference\"><span class=\"authors-reference\">M. Ostoja-starzewski</span>, <span class=\"title-reference\">Random field models of heterogeneous materials</span><span class=\"titleEvent-reference\">, <span class=\"titleEvent-reference-value\">Int. J. Solids Struct</span></span><span class=\"vol-reference\">, vol.<span class=\"vol-reference-value\">35</span></span><span class=\"pages-reference\">, pp.<span class=\"pages-reference-value\">2429-2455</span></span><span class=\"date-reference\">, <span class=\"date-reference-value\">1998</span>.</span></span><span class=\"identifiers-reference\"></span>\n</p>\n\n<p class=\"ref\" id=\"24642234\"><span class=\"citation-reference\"><span class=\"authors-reference\">M. Ostoja-starzewski</span>, <span class=\"title-reference\">Material spatial randomness: from statistical to representative volume element</span><span class=\"titleEvent-reference\">, <span class=\"titleEvent-reference-value\">Prob. Eng. Mech</span></span><span class=\"vol-reference\">, vol.<span class=\"vol-reference-value\">21</span></span><span class=\"pages-reference\">, pp.<span class=\"pages-reference-value\">112-132</span></span><span class=\"date-reference\">, <span class=\"date-reference-value\">2006</span>.</span></span><span class=\"identifiers-reference\"></span>\n</p>\n\n<p class=\"ref\" id=\"24642235\"><span class=\"citation-reference\"><span class=\"authors-reference\">G. Papanicolaou and S. Varadhan</span>, <span class=\"title-reference\">Boundary Value Problems with Rapidly Oscillating Random Coefficients</span><span class=\"pages-reference\">, pp.<span class=\"pages-reference-value\">835-873</span></span><span class=\"date-reference\">, <span class=\"date-reference-value\">1978</span>.</span></span><span class=\"identifiers-reference\"></span>\n</p>\n\n<p class=\"ref\" id=\"24642236\"><span class=\"citation-reference\"><span class=\"authors-reference\">C. Pelissou, J. Baccou, Y. Monerie, and F. Perales</span>, <span class=\"title-reference\">Determination of the size of the representative volume element for random quasi-brittle composites</span><span class=\"titleEvent-reference\">, <span class=\"titleEvent-reference-value\">Int. J. Sol. Struct</span></span><span class=\"vol-reference\">, vol.<span class=\"vol-reference-value\">46</span></span><span class=\"pages-reference\">, pp.<span class=\"pages-reference-value\">2842-2855</span></span><span class=\"date-reference\">, <span class=\"date-reference-value\">2009</span>.</span></span><span class=\"identifiers-reference\"><span class=\"url-reference\"><br>\nURL : <a class=\"url-reference-value\" target=\"_blank\" href=\"https://hal.archives-ouvertes.fr/hal-02095427\">https://hal.archives-ouvertes.fr/hal-02095427</a></span></span>\n</p>\n\n<p class=\"ref\" id=\"24642237\"><span class=\"citation-reference\"><span class=\"authors-reference\">P. Castañeda and P. </span>, <span class=\"title-reference\">Second-order homogeneisation estimates for nonlinear composites incorporating field fluctuations: I-theory</span><span class=\"titleEvent-reference\">, <span class=\"titleEvent-reference-value\">J. Mech. Phys. Solids</span></span><span class=\"vol-reference\">, vol.<span class=\"vol-reference-value\">50</span></span><span class=\"pages-reference\">, pp.<span class=\"pages-reference-value\">737-757</span></span><span class=\"date-reference\">, <span class=\"date-reference-value\">2002</span>.</span></span><span class=\"identifiers-reference\"></span>\n</p>\n\n<p class=\"ref\" id=\"24642238\"><span class=\"citation-reference\"><span class=\"authors-reference\">P. Castañeda, P. Suquet, and P. </span>, <span class=\"title-reference\">Nonlinear composites</span><span class=\"titleEvent-reference\">, <span class=\"titleEvent-reference-value\">Advances in Applied Mechanics</span></span><span class=\"vol-reference\">, vol.<span class=\"vol-reference-value\">34</span></span><span class=\"pages-reference\">, pp.<span class=\"pages-reference-value\">213-302</span></span><span class=\"date-reference\">, <span class=\"date-reference-value\">1997</span>.</span></span><span class=\"identifiers-reference\"></span>\n</p>\n\n<p class=\"ref\" id=\"24642239\"><span class=\"citation-reference\"><span class=\"authors-reference\">P. Castañeda, P. Willis, and J. </span>, <span class=\"title-reference\">The effect of spatial distribution on the effective behavior of composite materials and cracked media</span><span class=\"titleEvent-reference\">, <span class=\"titleEvent-reference-value\">J. Mech. Phys. Solids</span></span><span class=\"vol-reference\">, vol.<span class=\"vol-reference-value\">43</span></span><span class=\"issue-reference\">, issue.<span class=\"issue-reference-value\">12</span></span><span class=\"pages-reference\">, pp.<span class=\"pages-reference-value\">1919-1951</span></span><span class=\"date-reference\">, <span class=\"date-reference-value\">1995</span>.</span></span><span class=\"identifiers-reference\"></span>\n</p>\n\n<p class=\"ref\" id=\"24642240\"><span class=\"citation-reference\"><span class=\"authors-reference\">S. Ranganathan and M. Ostoja-starzewski</span>, <span class=\"title-reference\">Scaling function, anisotropy and the size of RVE in elastic random polycrystals</span><span class=\"titleEvent-reference\">, <span class=\"titleEvent-reference-value\">J. Mech. Phys. Solids</span></span><span class=\"vol-reference\">, vol.<span class=\"vol-reference-value\">56</span></span><span class=\"pages-reference\">, pp.<span class=\"pages-reference-value\">2773-2791</span></span><span class=\"date-reference\">, <span class=\"date-reference-value\">2008</span>.</span></span><span class=\"identifiers-reference\"></span>\n</p>\n\n<p class=\"ref\" id=\"24642241\"><span class=\"citation-reference\"><span class=\"authors-reference\">A. Reuss</span>, <span class=\"title-reference\">Calculation of the flow limits of mixed crystals on the basis of the plasticity of mono-crystals</span><span class=\"titleEvent-reference\">, <span class=\"titleEvent-reference-value\">Z. Angew. Math. Mech</span></span><span class=\"vol-reference\">, vol.<span class=\"vol-reference-value\">9</span></span><span class=\"pages-reference\">, pp.<span class=\"pages-reference-value\">49-58</span></span><span class=\"date-reference\">, <span class=\"date-reference-value\">1929</span>.</span></span><span class=\"identifiers-reference\"></span>\n</p>\n\n<p class=\"ref\" id=\"24642242\"><span class=\"citation-reference\"><span class=\"authors-reference\">M. Rintoul and S. Torquato</span>, <span class=\"title-reference\">Reconstruction of the structure of dispersions</span><span class=\"titleEvent-reference\">, <span class=\"titleEvent-reference-value\">J. Colloid Interface Sci</span></span><span class=\"vol-reference\">, vol.<span class=\"vol-reference-value\">186</span></span><span class=\"issue-reference\">, issue.<span class=\"issue-reference-value\">2</span></span><span class=\"pages-reference\">, pp.<span class=\"pages-reference-value\">467-476</span></span><span class=\"date-reference\">, <span class=\"date-reference-value\">1997</span>.</span></span><span class=\"identifiers-reference\"></span>\n</p>\n\n<p class=\"ref\" id=\"24642243\"><span class=\"citation-reference\"><span class=\"authors-reference\">K. Sab</span>, <span class=\"title-reference\">On the homogenization and the simulation of random materials</span><span class=\"titleEvent-reference\">, <span class=\"titleEvent-reference-value\">Eur. J. Mech. A/Solids</span></span><span class=\"vol-reference\">, vol.<span class=\"vol-reference-value\">11</span></span><span class=\"pages-reference\">, pp.<span class=\"pages-reference-value\">585-607</span></span><span class=\"date-reference\">, <span class=\"date-reference-value\">1992</span>.</span></span><span class=\"identifiers-reference\"></span>\n</p>\n\n<p class=\"ref\" id=\"24642244\"><span class=\"citation-reference\"><span class=\"authors-reference\">M. Salmi</span>, <span class=\"title-reference\">Homogénéisation des composites linéaires: étude de la variabilité des comportements</span><span class=\"date-reference\">, <span class=\"date-reference-value\">2011</span>.</span></span><span class=\"identifiers-reference\"></span>\n</p>\n\n<p class=\"ref\" id=\"24642245\"><span class=\"citation-reference\"><span class=\"authors-reference\">M. Salmi, F. Auslender, M. Bornert, and M. Fogli</span>, <span class=\"title-reference\">Various estimates of representative volume element sizes based on a statistical analysis of the apparent behavior of random linear composites</span><span class=\"titleEvent-reference\">, <span class=\"titleEvent-reference-value\">Comptes Rendus Mécanique</span></span><span class=\"date-reference\">, <span class=\"date-reference-value\">2012</span>.</span></span><span class=\"identifiers-reference\"><span class=\"url-reference\"><br>\nURL : <a class=\"url-reference-value\" target=\"_blank\" href=\"https://hal.archives-ouvertes.fr/hal-01157361\">https://hal.archives-ouvertes.fr/hal-01157361</a></span></span>\n</p>\n\n<p class=\"ref\" id=\"24642246\"><span class=\"citation-reference\"><span class=\"authors-reference\">E. Sanchez-palencia</span><span class=\"titleEvent-reference\">, <span class=\"titleEvent-reference-value\"></span></span><span class=\"vol-reference\">, vol.<span class=\"vol-reference-value\">272</span></span><span class=\"date-reference\">, <span class=\"date-reference-value\">1987</span>.</span></span><span class=\"identifiers-reference\"></span>\n</p>\n\n<p class=\"ref\" id=\"24642247\"><span class=\"citation-reference\"><span class=\"authors-reference\">J. Schoberl, H. Gerstmayr, and R. Gaisbauer</span>, <span class=\"title-reference\">Netgen -Automatic mesh generator</span><span class=\"date-reference\">, <span class=\"date-reference-value\">2003</span>.</span></span><span class=\"identifiers-reference\"></span>\n</p>\n\n<p class=\"ref\" id=\"24642248\"><span class=\"citation-reference\"><span class=\"authors-reference\">C. Stolz and A. Zaoui</span>, <span class=\"title-reference\">Analyse morphologique et approches variationnelles du comportement d'un milieu élastique hétérogène</span><span class=\"titleEvent-reference\">, <span class=\"titleEvent-reference-value\">C.R. Acad. Sci</span></span><span class=\"vol-reference\">, vol.<span class=\"vol-reference-value\">312</span></span><span class=\"pages-reference\">, pp.<span class=\"pages-reference-value\">143-150</span></span><span class=\"date-reference\">, <span class=\"date-reference-value\">1991</span>.</span></span><span class=\"identifiers-reference\"></span>\n</p>\n\n<p class=\"ref\" id=\"24642249\"><span class=\"citation-reference\"><span class=\"authors-reference\">W. Voigt</span>, <span class=\"title-reference\">1889. über die beziehung zwischen den beiden elasticitätsconstanten isotroper körper</span><span class=\"titleEvent-reference\">, <span class=\"titleEvent-reference-value\">Ann. Phys. (Leipzig)</span></span><span class=\"vol-reference\">, vol.<span class=\"vol-reference-value\">38</span></span><span class=\"pages-reference\">, pp.<span class=\"pages-reference-value\">573-587</span></span></span><span class=\"identifiers-reference\"></span>\n</p>\n\n<p class=\"ref\" id=\"24642250\"><span class=\"citation-reference\"><span class=\"authors-reference\">L. Walpole</span>, <span class=\"title-reference\">Elastic Behavior of Composite Materials: Theoretical Foundations</span><span class=\"vol-reference\">, vol.<span class=\"vol-reference-value\">21</span></span><span class=\"pages-reference\">, pp.<span class=\"pages-reference-value\">160-242</span></span><span class=\"date-reference\">, <span class=\"date-reference-value\">1981</span>.</span></span><span class=\"identifiers-reference\"></span>\n</p>\n\n<p class=\"ref\" id=\"24642251\"><span class=\"citation-reference\"><span class=\"authors-reference\">J. Willis</span>, <span class=\"title-reference\">Bounds and self-consistent estimates for the overall properties of anisotropic composites</span><span class=\"titleEvent-reference\">, <span class=\"titleEvent-reference-value\">J. Mech. Phys. Solids</span></span><span class=\"vol-reference\">, vol.<span class=\"vol-reference-value\">25</span></span><span class=\"pages-reference\">, pp.<span class=\"pages-reference-value\">185-202</span></span><span class=\"date-reference\">, <span class=\"date-reference-value\">1977</span>.</span></span><span class=\"identifiers-reference\"></span>\n</p>\n\n<p class=\"ref\" id=\"24642252\"><span class=\"citation-reference\"><span class=\"authors-reference\">J. Willis</span>, <span class=\"title-reference\">Variational and related methods for the overall properties of composites</span><span class=\"titleEvent-reference\">, <span class=\"titleEvent-reference-value\">Adv. Appl. Mech</span></span><span class=\"vol-reference\">, vol.<span class=\"vol-reference-value\">21</span></span><span class=\"pages-reference\">, pp.<span class=\"pages-reference-value\">1-78</span></span><span class=\"date-reference\">, <span class=\"date-reference-value\">1981</span>.</span></span><span class=\"identifiers-reference\"></span>\n</p>\n\n<p class=\"ref\" id=\"24642253\"><span class=\"citation-reference\"><span class=\"authors-reference\">F. Willot and . Jeulin</span>, <span class=\"title-reference\">Elastic behavior of composites containing boolean random sets of inhomogeneities</span><span class=\"titleEvent-reference\">, <span class=\"titleEvent-reference-value\">Int. J. Eng. Sci</span></span><span class=\"vol-reference\">, vol.<span class=\"vol-reference-value\">47</span></span><span class=\"pages-reference\">, pp.<span class=\"pages-reference-value\">313-324</span></span><span class=\"date-reference\">, <span class=\"date-reference-value\">2009</span>.</span></span><span class=\"identifiers-reference\"><span class=\"url-reference\"><br>\nURL : <a class=\"url-reference-value\" target=\"_blank\" href=\"https://hal.archives-ouvertes.fr/hal-00426398\">https://hal.archives-ouvertes.fr/hal-00426398</a></span></span>\n</p>\n\n<p class=\"ref\" id=\"24642254\"><span class=\"citation-reference\"><span class=\"authors-reference\">F. Willot, Y. Pellegrini, and P. Ponte-castañeda</span>, <span class=\"title-reference\">Localization of elastic deformation in strongly anisotropic, porous, linear materials with periodic microstructures: exact solutions and dilute expansions</span><span class=\"titleEvent-reference\">, <span class=\"titleEvent-reference-value\">J. Mech. Phys. Solids</span></span><span class=\"vol-reference\">, vol.<span class=\"vol-reference-value\">56</span></span><span class=\"issue-reference\">, issue.<span class=\"issue-reference-value\">4</span></span><span class=\"pages-reference\">, pp.<span class=\"pages-reference-value\">1245-1268</span></span><span class=\"date-reference\">, <span class=\"date-reference-value\">2008</span>.</span></span><span class=\"identifiers-reference\"><span class=\"url-reference\"><br>\nURL : <a class=\"url-reference-value\" target=\"_blank\" href=\"https://hal.archives-ouvertes.fr/cea-00412543\">https://hal.archives-ouvertes.fr/cea-00412543</a></span></span>\n</p>\n\n</body></html>"},"version":3}